{
  "response_code": 0,
  "results": [
    {
      "category": "Mythology",
      "type": "multiple",
      "difficulty": "easy",
      "question": "Who was the only god from Greece who did not get a name change in Rome?",
      "correct_answer": "Apollo",
      "incorrect_answers": ["Zeus", "Hermes", "Poseidon"]
    },
    {
      "category": "Mythology",
      "type": "multiple",
      "difficulty": "easy",
      "question": "The ancient Roman god of war was commonly known as which of the following?",
      "correct_answer": "Mars",
      "incorrect_answers": ["Jupiter", "Mercury", "Venus"]
    },
    {
      "category": "Mythology",
      "type": "multiple",
      "difficulty": "easy",
      "question": "Who was the King of Gods in Ancient Greek mythology?",
      "correct_answer": "Zeus",
      "incorrect_answers": ["Hera", "Poseidon", "Ares"]
    },
    {
      "category": "Mythology",
      "type": "multiple",
      "difficulty": "easy",
      "question": "Which Greek & Roman god was known as the god of music, truth and prophecy, healing, the sun and light, plague, poetry, and more?",
      "correct_answer": "Apollo",
      "incorrect_answers": ["Athena", "Hermes", "Dionysus"]
    },
    {
      "category": "Mythology",
      "type": "multiple",
      "difficulty": "easy",
      "question": "The Greek god Poseidon was the god of what?",
      "correct_answer": "The Sea",
      "incorrect_answers": ["The Sky", "The Underworld", "The Sun"]
    },
    {
      "category": "Mythology",
      "type": "multiple",
      "difficulty": "easy",
      "question": "Which figure from Greek mythology traveled to the underworld to return his wife Eurydice to the land of the living?",
      "correct_answer": "Orpheus",
      "incorrect_answers": ["Heracles", "Perseus", "Theseus"]
    },
    {
      "category": "Mythology",
      "type": "multiple",
      "difficulty": "easy",
      "question": "In Greek mythology, who is the god of wine?",
      "correct_answer": "Dionysus",
      "incorrect_answers": ["Hades", "Apollo", "Hermes"]
    },
    {
      "category": "Mythology",
      "type": "multiple",
      "difficulty": "easy",
      "question": "In most traditions, who was the wife of Zeus?",
      "correct_answer": "Hera",
      "incorrect_answers": ["Athena", "Aphrodite", "Artemis"]
    },
    {
      "category": "Mythology",
      "type": "multiple",
      "difficulty": "easy",
      "question": "What mythology did the god \"Apollo\" come from?",
      "correct_answer": "Greek and Roman",
      "incorrect_answers": ["Norse", "Egyptian", "Hindu"]
    },
    {
      "category": "Mythology",
      "type": "multiple",
      "difficulty": "easy",
      "question": "What mythological creatures have women's faces and vultures' bodies?",
      "correct_answer": "Harpies",
      "incorrect_answers": ["Sirens", "Gorgons", "Centaurs"]
    }
  ]
}
